outlook_account_generator/__init__.py
outlook_account_generator/client.py
outlook_account_generator-1.0.2.dist-info/METADATA
outlook_account_generator-1.0.2.dist-info/WHEEL
outlook_account_generator-1.0.2.dist-info/top_level.txt
outlook_account_generator-1.0.2.dist-info/RECORD
