Metadata-Version: 2.4
Name: outlook-account-generator
Version: 1.0.2
Summary: A Python wrapper to generate real Outlook/Hotmail accounts and fetch OTPs via JSON.
Home-page: https://rapidapi.com/EymenTakak/api/temp-outlook-api
Author: TempOutlookAPI
Author-email: support@tempoutlookapi.com
Classifier: Programming Language :: Python :: 3
Classifier: License :: OSI Approved :: MIT License
Classifier: Operating System :: OS Independent
Requires-Python: >=3.6
Requires-Dist: requests
Dynamic: author
Dynamic: author-email
Dynamic: classifier
Dynamic: description
Dynamic: description-content-type
Dynamic: home-page
Dynamic: requires-dist
Dynamic: requires-python
Dynamic: summary
